{"st": "72", "st+1": "39", "reward": 0.0038821548223495483, "time": 475.0631535053253, "type": "INCONSISTENCY", "json": {"framework": "PyTorch", "input_shape": [32, 32, 3], "network": [{"name": "Sigmoid", "params": {}}, {"name": "Rsqrt", "params": {}}, {"name": "Tile", "params": {"multiples": [3, 2, 3], "tensor_space": 4}}, {"name": "Rsqrt", "params": {}}, {"name": "Square", "params": {}}, {"name": "Rsqrt", "params": {}}, {"name": "Slice", "params": {"tensor_space": 4, "begin": [0, 13, 37, 5], "size": [100, 40, 24, 2]}}, {"name": "GlobalMaxPool2d", "params": {}}, {"name": "Sigmoid", "params": {}}, {"name": "Dense", "params": {"in_features": 2, "out_features": 771, "bias": true}}, {"name": "Dense", "params": {"in_features": 771, "out_features": 10}}, {"name": "Softmax"}]}}