{"st": "72", "st+1": "29", "reward": 0.3957875967025757, "time": 138.75501370429993, "type": "INCONSISTENCY", "json": {"framework": "TensorFlow", "input_shape": [32, 32, 3], "network": [{"name": "Cast", "params": {"target_dtype": "float32"}}, {"name": "LeakyReLU", "params": {"alpha": 0.008161813297417417}}, {"name": "Cast", "params": {"target_dtype": "float32"}}, {"name": "Sigmoid", "params": {}}, {"name": "Flatten", "params": {}}, {"name": "Dense", "params": {"in_features": 3072, "out_features": 10}}, {"name": "Softmax"}]}}